config_py2/__init__.py
config_py2/config_entrypoint.py
config_py2/loader.py
config_py2-1.3.3.dist-info/LICENSE
config_py2-1.3.3.dist-info/METADATA
config_py2-1.3.3.dist-info/WHEEL
config_py2-1.3.3.dist-info/entry_points.txt
config_py2-1.3.3.dist-info/top_level.txt
config_py2-1.3.3.dist-info/RECORD
