Metadata-Version: 2.1
Name: config-py2
Version: 1.3.3
Summary: A Config Management CLI Tool similar to dynaconf for python 2 and above
Home-page: https://gitlab.com/chalukyaj/config-manager-python2
Author: Chalukya
Author-email: chalukya@gmail.com
License: MIT
Project-URL: Bug Tracker, https://gitlab.com/chalukyaj/config-manager-python2/issues
Keywords: config,cli,toml,json,yaml,python2,python 2.x,dynaconf
Platform: UNKNOWN
Classifier: Intended Audience :: Developers
Classifier: Topic :: Software Development :: Documentation
Classifier: License :: OSI Approved :: MIT License
Classifier: Programming Language :: Python :: 2.7
Classifier: Operating System :: OS Independent
Requires-Python: >=2.7
Requires-Dist: click (==7.1.2)
Requires-Dist: PyYAML (==5.4.1)
Requires-Dist: toml (==0.10.2)
Requires-Dist: ujson (==2.0.3)
